fedgp/__init__.py
fedgp/data.py
fedgp-0.1.0.dist-info/WHEEL
fedgp-0.1.0.dist-info/METADATA
fedgp-0.1.0.dist-info/RECORD
