Metadata-Version: 2.1
Name: fedgp
Version: 0.1.0
Summary: A package for model agreggation in federated learning using Gaussian processes
Author: Santiago
Author-email: 16252054+sssilvar@users.noreply.github.com
Requires-Python: >=3.8,<4.0
Classifier: Programming Language :: Python :: 3
Classifier: Programming Language :: Python :: 3.8
Classifier: Programming Language :: Python :: 3.9
Requires-Dist: sklearn (>=0.0,<0.1)
